hightouch/__init__.py
hightouch/sdk.py
hightouch/models/__init__.py
hightouch/models/operations/__init__.py
hightouch/models/operations/createdestination.py
hightouch/models/operations/createmodel.py
hightouch/models/operations/createsource.py
hightouch/models/operations/createsync.py
hightouch/models/operations/getdestination.py
hightouch/models/operations/getmodel.py
hightouch/models/operations/getsource.py
hightouch/models/operations/getsync.py
hightouch/models/operations/listdestination.py
hightouch/models/operations/listmodel.py
hightouch/models/operations/listsource.py
hightouch/models/operations/listsync.py
hightouch/models/operations/listsyncruns.py
hightouch/models/operations/triggerrun.py
hightouch/models/operations/triggerruncustom.py
hightouch/models/operations/updatedestination.py
hightouch/models/operations/updatemodel.py
hightouch/models/operations/updatesource.py
hightouch/models/operations/updatesync.py
hightouch/models/shared/__init__.py
hightouch/models/shared/cronschedule.py
hightouch/models/shared/dbtschedule.py
hightouch/models/shared/destination.py
hightouch/models/shared/destinationcreate.py
hightouch/models/shared/destinationupdate.py
hightouch/models/shared/internalservererror.py
hightouch/models/shared/interval.py
hightouch/models/shared/intervalschedule.py
hightouch/models/shared/intervalunit.py
hightouch/models/shared/model.py
hightouch/models/shared/modelcreate.py
hightouch/models/shared/modelupdate.py
hightouch/models/shared/record_day_boolean_or_undefined_.py
hightouch/models/shared/source.py
hightouch/models/shared/sourcecreate.py
hightouch/models/shared/sourceupdate.py
hightouch/models/shared/sync.py
hightouch/models/shared/synccreate.py
hightouch/models/shared/syncrun.py
hightouch/models/shared/syncrunstatus.py
hightouch/models/shared/syncstatus.py
hightouch/models/shared/syncupdate.py
hightouch/models/shared/triggerruncustominput.py
hightouch/models/shared/triggerruninput.py
hightouch/models/shared/triggerrunoutput.py
hightouch-1.31.0.dist-info/METADATA
hightouch-1.31.0.dist-info/WHEEL
hightouch-1.31.0.dist-info/top_level.txt
hightouch-1.31.0.dist-info/RECORD
